tornetx/__init__.py
tornetx/banner.py
tornetx/tornetx.py
tornetx/utils.py
tornetx-2.1.4.dist-info/LICENSE
tornetx-2.1.4.dist-info/METADATA
tornetx-2.1.4.dist-info/WHEEL
tornetx-2.1.4.dist-info/entry_points.txt
tornetx-2.1.4.dist-info/top_level.txt
tornetx-2.1.4.dist-info/RECORD
